iyi/__init__.py
iyi/iyi.py
iyi-0.2.0.dist-info/METADATA
iyi-0.2.0.dist-info/WHEEL
iyi-0.2.0.dist-info/entry_points.txt
iyi-0.2.0.dist-info/top_level.txt
iyi-0.2.0.dist-info/RECORD
